poetry_lock_listener/__init__.py
poetry_lock_listener/_version.py
poetry_lock_listener/lock_diff.py
poetry_lock_listener/lock_listener_config.py
poetry_lock_listener/lock_spec.py
poetry_lock_listener/plugin.py
poetry_lock_listener/util.py
poetry_lock_listener-0.2.4.dist-info/METADATA
poetry_lock_listener-0.2.4.dist-info/WHEEL
poetry_lock_listener-0.2.4.dist-info/entry_points.txt
poetry_lock_listener-0.2.4.dist-info/licenses/LICENSE
poetry_lock_listener-0.2.4.dist-info/RECORD
