Metadata-Version: 2.4
Name: poetry-lock-listener
Version: 0.2.4
Summary: 
License-File: LICENSE
Author: Your Name
Author-email: you@example.com
Requires-Python: >=3.10,<4.0
Classifier: Programming Language :: Python :: 3
Classifier: Programming Language :: Python :: 3.10
Classifier: Programming Language :: Python :: 3.11
Classifier: Programming Language :: Python :: 3.12
Classifier: Programming Language :: Python :: 3.13
Classifier: Programming Language :: Python :: 3.14
Requires-Dist: cleo (>=2.1.0,<3.0.0)
Requires-Dist: poetry (>=1.7.1)
Requires-Dist: tomli (>=2.0.1,<3.0.0)
